mcp_sbom/__init__.py
mcp_sbom/server.py
mseep_mcp_sbom-0.1.4.dist-info/METADATA
mseep_mcp_sbom-0.1.4.dist-info/WHEEL
mseep_mcp_sbom-0.1.4.dist-info/entry_points.txt
mseep_mcp_sbom-0.1.4.dist-info/top_level.txt
mseep_mcp_sbom-0.1.4.dist-info/RECORD
