Metadata-Version: 2.4
Name: mseep-mcp-sbom
Version: 0.1.4
Summary: MCP server to perform a scan and produce an SBOM
Author-email: mseep <support@skydeck.ai>
Requires-Python: >=3.12
Requires-Dist: mcp[cli]>=1.6.0
Requires-Dist: python-dotenv>=1.0.1
